eoms/__init__.py
eoms/__main__.py
eoms/py.typed
eoms/agents/__init__.py
eoms/agents/algo_agent.py
eoms/agents/base.py
eoms/agents/pnl_agent.py
eoms/brokers/__init__.py
eoms/brokers/base.py
eoms/brokers/fix44_broker.py
eoms/brokers/null_broker.py
eoms/brokers/resilient_sim_broker.py
eoms/brokers/sim_broker.py
eoms/core/__init__.py
eoms/core/chaos.py
eoms/core/circuit_breaker.py
eoms/core/compliance.py
eoms/core/config.py
eoms/core/eventbus.py
eoms/core/eventstore.py
eoms/core/logging.py
eoms/core/metrics.py
eoms/core/plugin.py
eoms/core/recovery.py
eoms/core/resilience.py
eoms/core/scheduler.py
eoms/core/security.py
eoms/feeds/__init__.py
eoms/feeds/base.py
eoms/feeds/random_feed.py
eoms/feeds/websocket_adapter.py
eoms/gui/__init__.py
eoms/gui/__main__.py
eoms/gui/main_window.py
eoms/gui/reactive_models.py
eoms/gui/theme_manager.py
eoms/gui/virtual_table.py
eoms/gui/window_manager.py
eoms/gui/widgets/__init__.py
eoms/gui/widgets/algo_manager.py
eoms/gui/widgets/order_manager.py
eoms/gui/widgets/order_ticket.py
eoms/gui/widgets/pnl_window.py
eoms/gui/widgets/positions_manager.py
eoms/plugins/__init__.py
eoms/plugins/sample.py
eoms/strategies/__init__.py
eoms/strategies/base.py
eoms-1.6.0.dist-info/licenses/LICENSE
eoms-1.6.0.dist-info/METADATA
eoms-1.6.0.dist-info/WHEEL
eoms-1.6.0.dist-info/entry_points.txt
eoms-1.6.0.dist-info/top_level.txt
eoms-1.6.0.dist-info/RECORD
